openapi/__init__.py
openapi/cli.py
openapi/data/__init__.py
openapi/data/db.py
openapi/data/dump.py
openapi/data/exc.py
openapi/data/fields.py
openapi/data/validate.py
openapi/data/view.py
openapi/db/__init__.py
openapi/db/columns.py
openapi/db/commands.py
openapi/db/container.py
openapi/db/dbmodel.py
openapi/db/migrations.py
openapi/db/openapi/alembic.ini.mako
openapi/db/openapi/env.py
openapi/db/openapi/script.py.mako
openapi/db/path.py
openapi/exc.py
openapi/json.py
openapi/logger.py
openapi/middleware.py
openapi/pagination/__init__.py
openapi/pagination/create.py
openapi/pagination/cursor.py
openapi/pagination/offset.py
openapi/pagination/pagination.py
openapi/pagination/search.py
openapi/py.typed
openapi/rest.py
openapi/sentry.py
openapi/spec/__init__.py
openapi/spec/hdrs.py
openapi/spec/operation.py
openapi/spec/path.py
openapi/spec/redoc.py
openapi/spec/server.py
openapi/spec/spec.py
openapi/spec/utils.py
openapi/testing.py
openapi/types.py
openapi/tz.py
openapi/utils.py
openapi/ws/__init__.py
openapi/ws/channel.py
openapi/ws/channels.py
openapi/ws/errors.py
openapi/ws/manager.py
openapi/ws/path.py
openapi/ws/pubsub.py
openapi/ws/rpc.py
openapi/ws/utils.py
aio_openapi-3.2.1.dist-info/LICENSE
aio_openapi-3.2.1.dist-info/METADATA
aio_openapi-3.2.1.dist-info/WHEEL
aio_openapi-3.2.1.dist-info/RECORD
