Metadata-Version: 2.1
Name: aio-openapi
Version: 3.2.1
Summary: Minimal OpenAPI asynchronous server application
Home-page: https://github.com/quantmind/aio-openapi
License: BSD-3-Clause
Author: Luca
Author-email: luca@quantmind.com
Requires-Python: >=3.8.1,<4
Classifier: Development Status :: 5 - Production/Stable
Classifier: Environment :: Web Environment
Classifier: Framework :: AsyncIO
Classifier: Intended Audience :: Developers
Classifier: License :: OSI Approved :: BSD License
Classifier: Operating System :: OS Independent
Classifier: Programming Language :: JavaScript
Classifier: Programming Language :: Python
Classifier: Programming Language :: Python :: 3
Classifier: Programming Language :: Python :: 3.9
Classifier: Programming Language :: Python :: 3.10
Classifier: Programming Language :: Python :: 3.11
Classifier: Programming Language :: Python :: 3.8
Classifier: Topic :: Internet
Classifier: Topic :: Internet :: WWW/HTTP
Classifier: Topic :: Software Development
Classifier: Topic :: Software Development :: Libraries
Classifier: Topic :: Software Development :: Libraries :: Application Frameworks
Classifier: Topic :: Software Development :: Libraries :: Python Modules
Classifier: Typing :: Typed
Provides-Extra: dev
Provides-Extra: docs
Requires-Dist: PyYAML (>=6.0,<7.0)
Requires-Dist: SQLAlchemy-Utils (>=0.41.1,<0.42.0)
Requires-Dist: SQLAlchemy[asyncio] (>=2.0.8,<3.0.0)
Requires-Dist: aiohttp (>=3.8.0,<4.0.0)
Requires-Dist: alembic (>=1.8.1,<2.0.0)
Requires-Dist: asyncpg (>=0.28.0,<0.29.0)
Requires-Dist: backports.zoneinfo (>=0.2.1,<0.3.0) ; python_version < "3.9"
Requires-Dist: click (>=8.0.3,<9.0.0)
Requires-Dist: email-validator (>=1.2.1,<2.0.0)
Requires-Dist: httptools (>=0.5.0,<0.6.0)
Requires-Dist: psycopg2-binary (>=2.9.2,<3.0.0)
Requires-Dist: python-dateutil (>=2.8.2,<3.0.0)
Requires-Dist: simplejson (>=3.17.2,<4.0.0)
Project-URL: Documentation, https://aio-openapi.readthedocs.io
Project-URL: Repository, https://github.com/quantmind/aio-openapi
Project-URL: issues, https://github.com/quantmind/aio-openapi/issues
Project-URL: repository, https://github.com/quantmind/aio-openapi
